StrateQueue/__init__.py
StrateQueue/api/__init__.py
StrateQueue/api/daemon.py
StrateQueue/brokers/__init__.py
StrateQueue/brokers/broker_base.py
StrateQueue/brokers/broker_factory.py
StrateQueue/brokers/broker_helpers.py
StrateQueue/brokers/Alpaca/alpaca_broker.py
StrateQueue/brokers/CCXT/__init__.py
StrateQueue/brokers/CCXT/ccxt_broker.py
StrateQueue/brokers/CCXT/exchange_config.py
StrateQueue/brokers/CCXT/exchange_selector.py
StrateQueue/brokers/IBKR/__init__.py
StrateQueue/brokers/IBKR/contracts.py
StrateQueue/brokers/IBKR/credential_check.py
StrateQueue/brokers/IBKR/ib_gateway_broker.py
StrateQueue/brokers/IBKR/ibkr_broker.py
StrateQueue/brokers/IBKR/account/__init__.py
StrateQueue/brokers/IBKR/account/account_manager.py
StrateQueue/brokers/IBKR/account/position_manager.py
StrateQueue/brokers/IBKR/orders/__init__.py
StrateQueue/brokers/IBKR/orders/base_order.py
StrateQueue/brokers/IBKR/orders/limit_order.py
StrateQueue/brokers/IBKR/orders/market_order.py
StrateQueue/brokers/IBKR/orders/order_manager.py
StrateQueue/brokers/IBKR/utils/__init__.py
StrateQueue/brokers/IBKR/utils/async_helpers.py
StrateQueue/brokers/IBKR/utils/connection.py
StrateQueue/cli/__init__.py
StrateQueue/cli/cli.py
StrateQueue/cli/command_factory.py
StrateQueue/cli/command_registry.py
StrateQueue/cli/commands/__init__.py
StrateQueue/cli/commands/base_command.py
StrateQueue/cli/commands/daemon_command.py
StrateQueue/cli/commands/deploy_command.py
StrateQueue/cli/commands/list_command.py
StrateQueue/cli/commands/setup_command.py
StrateQueue/cli/commands/status_command.py
StrateQueue/cli/commands/webui_command.py
StrateQueue/cli/formatters/__init__.py
StrateQueue/cli/formatters/base_formatter.py
StrateQueue/cli/formatters/info_formatter.py
StrateQueue/cli/parsers/__init__.py
StrateQueue/cli/parsers/base_parser.py
StrateQueue/cli/utils/__init__.py
StrateQueue/cli/utils/color_formatter.py
StrateQueue/cli/utils/command_help.py
StrateQueue/cli/utils/deploy_utils.py
stratequeue-0.5.1.dist-info/licenses/LICENSE
stratequeue-0.5.1.dist-info/METADATA
stratequeue-0.5.1.dist-info/WHEEL
stratequeue-0.5.1.dist-info/entry_points.txt
stratequeue-0.5.1.dist-info/top_level.txt
stratequeue-0.5.1.dist-info/RECORD
