Metadata-Version: 2.4
Name: StrateQueue
Version: 0.5.1
Summary: The fastest way from backtest to live trading
Author-email: Trading System Contributors <samuel.tinnerholm@gmail.com>
Maintainer-email: Trading System Contributors <samuel.tinnerholm@gmail.com>
License: AGPL-3.0
Project-URL: Homepage, https://github.com/StrateQueue/StrateQueue
Project-URL: Documentation, https://github.com/StrateQueue/StrateQueue#readme
Project-URL: Repository, https://github.com/StrateQueue/StrateQueue
Project-URL: Issues, https://github.com/StrateQueue/StrateQueue/issues
Project-URL: Changelog, https://github.com/StrateQueue/StrateQueue/releases
Keywords: trading,backtesting,live-trading,algorithmic-trading,financial-data,quantitative-finance,strategy-signals,alpaca-trading
Classifier: Development Status :: 4 - Beta
Classifier: Intended Audience :: Financial and Insurance Industry
Classifier: Intended Audience :: Developers
Classifier: Topic :: Office/Business :: Financial :: Investment
Classifier: Topic :: Scientific/Engineering :: Information Analysis
Classifier: License :: OSI Approved :: GNU Affero General Public License v3
Classifier: Programming Language :: Python :: 3
Classifier: Programming Language :: Python :: 3.10
Classifier: Operating System :: OS Independent
Requires-Python: >=3.10
License-File: LICENSE
Requires-Dist: pandas>=2.0.0
Requires-Dist: requests>=2.31.0
Requires-Dist: websocket-client>=1.6.0
Requires-Dist: python-dotenv>=1.0.0
Requires-Dist: alpaca-py>=0.40.0
Requires-Dist: ccxt>=4.4.96
Requires-Dist: questionary>=1.10.0
Requires-Dist: fastapi>=0.104.0
Requires-Dist: uvicorn[standard]>=0.24.0
Requires-Dist: python-multipart
Requires-Dist: httpx>=0.24.0
Requires-Dist: rich>=13.0.0
Requires-Dist: pydantic<2.12,>=2.0
Requires-Dist: yfinance==0.2.65
Requires-Dist: nest_asyncio>=1.5.0
Requires-Dist: empyrical>=0.5.5
Provides-Extra: interactive
Requires-Dist: questionary>=1.10.0; extra == "interactive"
Provides-Extra: backtesting
Requires-Dist: numpy<3,>=1.24; extra == "backtesting"
Requires-Dist: bokeh>=2.4.2; extra == "backtesting"
Requires-Dist: backtesting>=0.3.3; extra == "backtesting"
Provides-Extra: vectorbt
Requires-Dist: numpy<1.24,>=1.21; extra == "vectorbt"
Requires-Dist: numba<0.57,>=0.56; extra == "vectorbt"
Requires-Dist: vectorbt<0.29,>=0.26; extra == "vectorbt"
Requires-Dist: pandas<2.4,>=2.0; extra == "vectorbt"
Requires-Dist: scipy<2.0,>=1.9; extra == "vectorbt"
Requires-Dist: matplotlib<4.0,>=3.5; extra == "vectorbt"
Requires-Dist: plotly<7.0,>=5.0; extra == "vectorbt"
Requires-Dist: requests<3.0,>=2.31; extra == "vectorbt"
Requires-Dist: dill<0.5,>=0.3.6; extra == "vectorbt"
Requires-Dist: tqdm<5.0,>=4.64; extra == "vectorbt"
Requires-Dist: pytz>=2022.1; extra == "vectorbt"
Requires-Dist: python-dateutil<3.0,>=2.8; extra == "vectorbt"
Provides-Extra: backtrader
Requires-Dist: backtrader>=1.9.78.123; extra == "backtrader"
Provides-Extra: zipline
Requires-Dist: zipline-reloaded>=3.0; extra == "zipline"
Provides-Extra: bt
Requires-Dist: bt>=0.2.9; extra == "bt"
Provides-Extra: analytics
Requires-Dist: scipy>=1.11.0; extra == "analytics"
Requires-Dist: ta-lib>=0.4.0; extra == "analytics"
Provides-Extra: database
Requires-Dist: psycopg2-binary>=2.9.7; extra == "database"
Requires-Dist: redis>=4.6.0; extra == "database"
Provides-Extra: monitoring
Requires-Dist: prometheus-client>=0.17.0; extra == "monitoring"
Requires-Dist: structlog>=23.1.0; extra == "monitoring"
Provides-Extra: ibkr
Requires-Dist: ib_insync>=0.9.85; extra == "ibkr"
Provides-Extra: dev
Requires-Dist: pytest>=7.4.0; extra == "dev"
Requires-Dist: pytest-asyncio>=0.21.0; extra == "dev"
Requires-Dist: pytest-dependency>=0.5.1; extra == "dev"
Requires-Dist: pexpect>=4.8.0; extra == "dev"
Requires-Dist: black>=23.0.0; extra == "dev"
Requires-Dist: flake8>=6.0.0; extra == "dev"
Requires-Dist: mypy>=1.5.0; extra == "dev"
Requires-Dist: isort>=5.12.0; extra == "dev"
Requires-Dist: pre-commit>=3.0.0; extra == "dev"
Requires-Dist: pytest-cov>=4.1.0; extra == "dev"
Provides-Extra: full
Requires-Dist: numpy<3,>=1.24; extra == "full"
Requires-Dist: backtesting>=0.3.3; extra == "full"
Requires-Dist: zipline-reloaded>=3.0; extra == "full"
Requires-Dist: scipy>=1.11.0; extra == "full"
Requires-Dist: ta-lib>=0.4.0; extra == "full"
Requires-Dist: psycopg2-binary>=2.9.7; extra == "full"
Requires-Dist: redis>=4.6.0; extra == "full"
Requires-Dist: prometheus-client>=0.17.0; extra == "full"
Requires-Dist: structlog>=23.1.0; extra == "full"
Requires-Dist: questionary>=1.10.0; extra == "full"
Provides-Extra: all
Requires-Dist: numpy<3,>=1.24; extra == "all"
Requires-Dist: backtesting>=0.3.3; extra == "all"
Requires-Dist: vectorbt<0.29,>=0.25; extra == "all"
Requires-Dist: numba<0.57,>=0.56; extra == "all"
Requires-Dist: zipline-reloaded>=3.0; extra == "all"
Requires-Dist: bt>=0.2.9; extra == "all"
Requires-Dist: scipy>=1.11.0; extra == "all"
Requires-Dist: ta-lib>=0.4.0; extra == "all"
Requires-Dist: psycopg2-binary>=2.9.7; extra == "all"
Requires-Dist: redis>=4.6.0; extra == "all"
Requires-Dist: prometheus-client>=0.17.0; extra == "all"
Requires-Dist: structlog>=23.1.0; extra == "all"
Requires-Dist: questionary>=1.10.0; extra == "all"
Requires-Dist: backtrader>=1.9.78.123; extra == "all"
Dynamic: license-file
